{
	    "嘉義縣":{
        "番路鄉":{"ㄅ":[],"ㄆ":[],"ㄇ":["民和村","民和村下客庄","民和村半天岩","民和村沈厝仔","民和村岩仔","民和村岩仔後","民和村岩仔腳","民和村客庄","梅花一路","梅花七路","梅花二路","梅花三路","梅花五路","梅花六路"],"ㄈ":["番路村","番路村下石頭埔","番路村瓦厝仔","番路村坑底","番路村頂石頭埔","番路村番路"],"ㄉ":["大湖村下坪仔","大湖村大湖","大湖村五百恩仔","大湖村火燒寮","大湖村石腳桶","大湖村紅筆仔壽","大湖村凍子嶺","大湖村崁腳","大湖村茶科","大湖村湖尾","大湖村橫路","大湖村雙溪","頂番路"],"ㄊ":["潭情路"],"ㄋ":["內甕村仁義潭施工所","內甕村凸湖","內甕村瓦厝仔","內甕村竹山","內甕村明義新村","內甕村南勢坑","內甕村後坑仔","內甕村茅埔仔","內甕村崎腳","內甕村過溪仔"],"ㄌ":[],"ㄍ":["公田村","公田村大路仔","公田村石腳桶","公田村板仔龍","公田村厚𪞱仔","公田村破布湖","公田村馬厝","公田村崩山仔","公田村過龍仔","公田村隙頂","公田村潮州湖","公田村鞍頂","公田村魯古石","公田村蕉林","公田村龍美","公田村龍頭","公田村濫田仔","公興村","公興村下路","公興村下寮","公興村小公田","公興村中寮","公興村竹湖","公興村苦苓橋","公興村腦寮","公興村鞍腳","公興村龍美"],"ㄎ":[],"ㄏ":[],"ㄐ":["江西村","江西村三橋仔","江西村大宅仔","江西村平畑","江西村平園","江西村江西寮","江西村李厝","江西村南勢坑","江西村柿仔腳","江西村崎腳","江西村陳厝","江西村頂宅仔","江西村頂角仔","江西村劉厝"],"ㄑ":[],"ㄒ":["下坑村","下坑村下坑","下坑村北勢","下坑村竹圍仔","下坑村坑仔內","下坑村頂坑","下坑村菁仔宅","下坑村菜公店","新福村","新福村下宅仔","新福村大片田尾","新福村大庄","新福村五虎寮","新福村內坑","新福村公館仔","新福村崁腳","新福村第三農場","新福村許厝","新福村鳳梨園","新福村轆仔腳"],"ㄓ":[],"ㄔ":["觸口村","觸口村牛埔仔","觸口村車埕","觸口村埔尾","觸口村過溪仔","觸口村鳳梨農場","觸口村觸口"],"ㄕ":[],"ㄖ":["日安一街","日安二街"],"ㄗ":[],"ㄘ":["草山村山毛湖","草山村公田底","草山村水井","草山村半嶺","草山村永興","草山村草山","草山村總興"],"ㄙ":[],"ㄚ":[],"ㄛ":[],"ㄜ":[],"ㄝ":[],"ㄞ":[],"ㄟ":[],"ㄠ":[],"ㄡ":[],"ㄢ":[],"ㄣ":[],"ㄤ":[],"ㄥ":[],"ㄦ":[],"ㄧ":[],"ㄨ":[],"ㄩ":[]},
        "梅山鄉":{"ㄅ":["北榮街","北興街","半天村二坪仔","半天村下半天","半天村半天寮","半天村石壁仔","半天村頂半天","碧湖村堀尺嶺","碧湖村溪尾寮","碧湖村碧湖"],"ㄆ":["平等街"],"ㄇ":["民生街","梅北村三美庄","梅北村下田洋","梅北村田洋仔","梅北村華山","梅東村山仔腳","梅東村田洋仔","梅東村南市","梅東村樹林","梅南村梅仔山","梅南街"],"ㄈ":[],"ㄉ":["大坪路","大南村大片田","大南村大草埔","大南村水尾","大南村坑口","大南村南勢坑","大南村茅仔埔","大南村崁仔腳","大南村隘寮","大南村廍仔","大埔美園區二路","東榮街","東福街","東賢街","東興街","第一市場","稻寮路"],"ㄊ":["太平村下坑仔","太平村大坪","太平村坪路","太平村茅仔埔","太平村頂橋","太和村大里網","太和村公田","太和村太和","太和村全仔社","太和村油車寮","太和村社前湖","太和村社後坪","太和村柑仔宅","太和村洗人頭","太和村朕米糕","太和村匏仔園","太和村湖桶底","太和村蛤里味","太和村樟樹湖","太興村太興","太興村石古坪","太興村青園","太興村科仔腳","太興村柴筍林","太興村溪坪","太興村溪頭","太興村橫山"],"ㄋ":["南市場","南榮街","南興街"],"ㄌ":["龍眼村竹仔苓","龍眼村金鳳寮","龍眼村鹿寮坪","龍眼村龍眼林"],"ㄍ":["工業一路","公園西街","公園路","過山村大埤苓","過山村前過山","過山村後過山","過山村清水仔","過山村開元后","過山村鳳梨寮"],"ㄎ":["開元一街"],"ㄏ":["華山路","環北街","環南路"],"ㄐ":["吉祥街","健康街"],"ㄑ":[],"ㄒ":["玄廟路","西榮街","新市路","新榮街","新興路","學習街","興中路","霞山路"],"ㄓ":["中山路","中正路","中華街","中學路"],"ㄔ":["成功街"],"ㄕ":["山明街","社教路","雙溪村下雙溪","雙溪村田寮","雙溪村芎蕉山","雙溪村頂雙溪"],"ㄖ":["瑞里村九芎坪","瑞里村幼葉林","瑞里村坪頂","瑞里村科子林","瑞里村溪坪","瑞峰村二坪仔","瑞峰村日落頭","瑞峰村外寮","瑞峰村生毛樹","瑞峰村坔埔","瑞峰村倒交山","瑞峰村新興寮","榮興街"],"ㄗ":["圳北村下過溪","圳北村山仔頂","圳北村田頭崎","圳北村圳頭","圳北村頂過溪","圳北村麻園寮","圳北村麻園寮山","圳北村菁仔腳","圳南村九仔彎","圳南村三源","圳南村下樟湖","圳南村大樹腳","圳南村大豐","圳南村中樟湖","圳南村水底寮","圳南村梨仔腳","圳南村頂樟湖","圳南村瑞興"],"ㄘ":[],"ㄙ":[],"ㄚ":[],"ㄛ":[],"ㄜ":[],"ㄝ":[],"ㄞ":[],"ㄟ":[],"ㄠ":[],"ㄡ":[],"ㄢ":["安靖村水井仔","安靖村坑仔平","安靖村南靖寮","安靖村柿仔寮","安靖村湖底","安靖村詔安寮","安靖村樟普寮","安靖村錦湖腳"],"ㄣ":[],"ㄤ":[],"ㄥ":[],"ㄦ":[],"ㄧ":[],"ㄨ":[],"ㄩ":["永興村九芎坑","永興村下坑","永興村山美","永興村鼎瞰閂"]},
        "竹崎鄉":{"ㄅ":["白杞村","白杞村大坪","白杞村大埔","白杞村大園","白杞村中心崙","白杞村井仔頭","白杞村田中央","白杞村田仔坑","白杞村白杞","白杞村後山","白杞村泉州厝","白杞村湖仔嶺","白杞村溪坪","白杞村樟樹坪","白杞村學仔","白杞村橫路","白杞村嶺尾"],"ㄆ":[],"ㄇ":["民生路","民族路"],"ㄈ":["復金村","復金村木履寮","復金村水底寮","復金村白樹腳","復金村佳人山","復金村東復興","復金村鹿角叉","復金村復鐤金","復金村湖底","復金村溪湖","復興路","番仔路科"],"ㄉ":["緞繻村","緞繻村外埔","緞繻村石獅","緞繻村石壁腳","緞繻村松腳","緞繻村阿拔泉","緞繻村科尾","緞繻村科底","緞繻村紅南坑","緞繻村樟腦寮","緞繻村緞厝寮","緞繻村雙溪","緞繻村鹽菜甕"],"ㄊ":["桃源村","桃源村半天寮","桃源村石草田","桃源村竹頭尾","桃源村桃仔斜","桃源村桃源","桃源村軟𥕥","桃源村勝源","桃源村黃心寮","桃源村新寮坑","桃源村溫水溪仔","塘興村","塘興村下坪","塘興村坪頂","塘興村頂坪","塘興村無底潭","塘興村塘下寮","塘興村新社坑","塘興村賴厝"],"ㄋ":["內埔村","內埔村拔仔林","內埔村崁腳","內埔村圓潭","內埔村溪州","內埔村過坑","內埔村鹽水堀","內甕村"],"ㄌ":["鹿山路","鹿滿村","鹿滿村下溪心","鹿滿村水景頭","鹿滿村坑後","鹿滿村尾厝","鹿滿村頂溪心","鹿滿村鹿麻產","鹿滿村麻箕埔","鹿鳴路","龍山村","龍山村大庭","龍山村水尾仔","龍山村水道頭","龍山村瓦厝埔","龍山村南靖厝","龍山村崁仔腳","龍山村埤頂","龍山村崎腳","龍山村頂枋仔林","龍山村頂崎腳","龍山村菁埔","龍山村義崎","龍山村過坑"],"ㄍ":["光華村九芎坪","光華村水車寮","光華村石盤龍","光華村柑仔宅","光華村茄苳仔","光華村頂笨仔","光華村溪坪","光華村溪灘"],"ㄎ":["坑頭村","坑頭村大北勢","坑頭村內繳宮","坑頭村坑頭","坑頭村芎蕉湖","坑頭村復原莊","坑頭村順平厝","坑頭村檳榔宅"],"ㄏ":["宏運路","和平村","和平村山仔頂","和平村田寮","和平村坑仔坪","和平村羗仔科","和平村酒店","和平村頂蘇","和平村楠仔腳","和平村盧厝挖"],"ㄐ":["金獅村","金獅村出水坑","金獅村田仔腳","金獅村田仔寮","金獅村芊蓁坑","金獅村東湖仔","金獅村金獅寮"],"ㄑ":[],"ㄒ":[],"ㄓ":["中山路","中山路市場內攤位","中正路","中和村永和","中和村石棹","中和村奮起湖","中華路","中興路","竹民路","竹崎村","竹崎村三塊厝","竹崎村酒店","竹崎村舊車站"],"ㄔ":["盛市路"],"ㄕ":["沙坑村","沙坑村下厝","沙坑村大竹圍","沙坑村大松腳","沙坑村大湖","沙坑村木柵寮","沙坑村水坑","沙坑村羗仔寮","昇平村","昇平村山子頂","昇平村昇平","昇平村頂埔","昇平村菜公坑","昇平村菜堂頂","昇平村舊社","昇平村灣潭仔","盛市路","獅埜村","獅埜村五塊厝","獅埜村公館","獅埜村北勢坑","獅埜村圳頭坑","獅埜村東義","獅埜村林厝","獅埜村桃仔坑","獅埜村許厝","獅埜村獅子頭","獅埜村過溪仔"],"ㄖ":["仁壽村","仁壽村下寮","仁壽村下頭棟","仁壽村五號子","仁壽村水社寮","仁壽村交力坪","仁壽村風吹𥕥","仁壽村塘湖","仁壽村福建坪"],"ㄗ":["自由路","自由路二段","紫雲村","紫雲村大竹圍","紫雲村瓦磘","紫雲村坑口","紫雲村坑仔內","紫雲村崁腳","紫雲村鹿寮堀","紫雲村菜堂","紫雲村過溪","紫雲村橄欖腳","紫雲村頭前厝"],"ㄘ":[],"ㄙ":[],"ㄚ":[],"ㄛ":[],"ㄜ":[],"ㄝ":[],"ㄞ":[],"ㄟ":[],"ㄠ":[],"ㄡ":[],"ㄢ":[],"ㄣ":[],"ㄤ":[],"ㄥ":[],"ㄦ":[],"ㄧ":["義仁村下寮仔","義仁村內坑","義仁村半天寮","義仁村坪頂","義仁村番仔潭","義仁村溪角","義仁村橋仔頭","義仁村雙寬潭","義和村山子門","義和村火炭埔","義和村東義","義隆村","義隆村大坪頂","義隆村大圓尾","義隆村山知崙","義隆村科口","義隆村海豐科","義隆村新社坑","義隆村新社坑口"],"ㄨ":["文化路","文峰村","文峰村大坑","文峰村溪心寮","文峰村溪州仔","文峰村檨仔寮","灣橋村下厝坑","灣橋村五間厝","灣橋村王公園","灣橋村田尾","灣橋村石麻園","灣橋村朴子埔","灣橋村坑仔內","灣橋村李厝","灣橋村枋仔林","灣橋村埤堂","灣橋村崎腳","灣橋村灣橋"],"ㄩ":["元興路"]},
        "阿里山鄉":{"ㄅ":[],"ㄆ":[],"ㄇ":[],"ㄈ":["豐山村石鼓盤","豐山村豐山"],"ㄉ":["第一停車場攤販","第二停車場攤販","達邦村特富野","達邦村達邦","達邦村達德安"],"ㄊ":[],"ㄋ":[],"ㄌ":["里佳村里佳","來吉村內來吉","來吉村外來吉","來吉村來吉","樂野村石壁仔","樂野村米洋","樂野村湖底","樂野村福山","樂野村樂野"],"ㄍ":[],"ㄎ":[],"ㄏ":[],"ㄐ":[],"ㄑ":[],"ㄒ":["香林村二萬平","香林村西阿里山","香林村受鎮宮旁攤販","新美村新美","新美路"],"ㄓ":["中山村自忠","中山村南阿里山","中山村排雲","中正村東阿里山","中正村祝山"],"ㄔ":["茶山村茶山","茶山路"],"ㄕ":["十字村十字路","十字村哆囉嘕","十字村科仔林","十字村得恩亞納","十字村蕃薯寮","山美村山美","山美路"],"ㄖ":[],"ㄗ":[],"ㄘ":[],"ㄙ":[],"ㄚ":[],"ㄛ":[],"ㄜ":[],"ㄝ":[],"ㄞ":[],"ㄟ":[],"ㄠ":[],"ㄡ":[],"ㄢ":[],"ㄣ":[],"ㄤ":[],"ㄥ":[],"ㄦ":[],"ㄧ":["樂野村石壁仔","樂野村米洋","樂野村湖底","樂野村福山","樂野村樂野"],"ㄨ":[],"ㄩ":["樂野村石壁仔","樂野村米洋","樂野村湖底","樂野村福山","樂野村樂野"]},
        "中埔鄉":{"ㄅ":[],"ㄆ":["平實乙村","平實街"],"ㄇ":[],"ㄈ":["富收村庄內","富收村興化廍","富和路","富裕路","復興新村"],"ㄉ":["大義路","石硦村","石硦村天望崎","石硦村南勢埔","石硦村風櫃斗湖","石硦村藤寮","東興村","東興村八寶寮","東興村凍仔腳","頂中下街","頂埔村大埤","頂埔村王厝","頂埔村頂埔","頂埔村橫坑"],"ㄊ":["同仁村同仁","同仁村同仁","同仁村柚仔宅","同仁村荖園仔","同仁村圓山","潭情路"],"ㄋ":[],"ㄌ":["隆興村","隆興村下厝仔","隆興村大埕","隆興村石山店仔","隆興村竹圍仔","隆興村汴頭","隆興村枋樹腳","隆興村崎頭仔","隆興村湖仔厝","隆興村廍後","龍門村","龍門村龍山腳"],"ㄍ":[],"ㄎ":[],"ㄏ":["和美村司公廍","和美村後庄","和美路","和睦村公館","和睦村司公廍","和睦村後庄","和興村公館","和興村後庄","和興路"],"ㄐ":["金蘭村田寮","金蘭村赤蘭埔","金蘭村金蘭","金蘭村頂山門"],"ㄑ":[],"ㄒ":[],"ㄓ":["中山新村","中山路五段","中山路四段","中正新村","中正路","中埔村中埔","中埔村坪頂","中崙村中崙","中崙村分水嶺","中崙村玉井","中崙村石仔湖","中崙村石壁頭","中華路","中興西村","中興東村","忠仁街","忠和街","忠明路","忠信街","忠義路"],"ㄔ":[],"ㄕ":["十字路","石硦村","石硦村天望崎","石硦村南勢埔","石硦村風櫃斗湖","石硦村藤寮","社口村十塊厝","社口村下坑仔","社口村內埔","社口村芎蕉林","社口村社口","社口村番仔坑","社口村新庄仔","社口村過坑仔","社口村檨仔林","深坑村內灣","深坑村埔頂","深坑村深坑"],"ㄖ":["仁義路","瑞豐村坑尾","瑞豐村崁腳","瑞豐村陳厝","瑞豐村瑞豐"],"ㄗ":[],"ㄘ":[],"ㄙ":["三和路","三層村","三層村小石門","三層村官真閂","三層村茅埔","三層村桃仔寮","三層村崎頭仔","三層村糖部"],"ㄚ":[],"ㄛ":[],"ㄜ":[],"ㄝ":[],"ㄞ":[],"ㄟ":[],"ㄠ":[],"ㄡ":[],"ㄢ":[],"ㄣ":[],"ㄤ":[],"ㄥ":[],"ㄦ":[],"ㄧ":["義仁村","義仁村田寮仔","義仁村安家厝","義仁村後壁寮仔","義仁村挖仔厝","義仁村樹頭埔","鹽館村","鹽館村下庄仔","鹽館村溪州"],"ㄨ":["武德街","灣潭村","灣潭村下庄","灣潭村內湖","灣潭村松仔腳","灣潭村客庄","灣潭村後坑仔","灣潭村桃仔寮尾","灣潭村番仔田","灣潭村新寮","灣潭村溪仔口"],"ㄩ":["永安街","永樂新村","沄水村","沄水村大興","沄水村竹頭崎","沄水村沄水溪內","沄水街","裕民村","裕民村下庄","裕民村水仔尾","裕民村石頭厝","裕民村溪墘仔"]},
        "大埔鄉":{"ㄅ":[],"ㄆ":[],"ㄇ":[],"ㄈ":[],"ㄉ":["大埔五街","大埔村大埔","大埔村大埔自強巷","大埔路"],"ㄊ":[],"ㄋ":[],"ㄌ":[],"ㄍ":[],"ㄎ":[],"ㄏ":["和平村水寮","和平村石硤內","和平村馬頭山","和平村鳥埔","和平村雙溪"],"ㄐ":["茄苳村大山","茄苳村大茅埔","茄苳村竹圍仔","茄苳村坪林","茄苳村枋樹湖","茄苳村茄苳腳","茄苳村過山"],"ㄑ":["茄苳村大山","茄苳村大茅埔","茄苳村竹圍仔","茄苳村坪林","茄苳村枋樹湖","茄苳村茄苳腳","茄苳村過山"],"ㄒ":["西興村三重溪埔","西興村三脚石","西興村水底寮","西興村火燒寮","西興村牛稠坑","西興村竹崙","西興村茅埔仔","西興村風吹嶺","西興村草嶺","西興村菜瓜坪","西興村過山","西興村槺榔埔"],"ㄓ":[],"ㄔ":[],"ㄕ":[],"ㄖ":[],"ㄗ":["自由五街","自由六街","自由街"],"ㄘ":[],"ㄙ":[],"ㄚ":[],"ㄛ":[],"ㄜ":[],"ㄝ":[],"ㄞ":[],"ㄟ":[],"ㄠ":[],"ㄡ":[],"ㄢ":[],"ㄣ":[],"ㄤ":[],"ㄥ":[],"ㄦ":[],"ㄧ":[],"ㄨ":[],"ㄩ":["永樂村下新寮","永樂村內灣仔","永樂村牛舌埔","永樂村石井","永樂村南寮","永樂村後湖","永樂村眉仔陶","永樂村埔頂","永樂村湖底"]},
        "水上鄉":{"ㄅ":["八德街"],"ㄆ":[],"ㄇ":["民主街","民有街","民享街","民治街","名人街"],"ㄈ":["福德街"],"ㄉ":["大堀村","大堀村大堀尾","大堀村江竹仔腳","大堀村頂過溝","大崙村二重溝","大崙村大崙","店興街"],"ㄊ":["塗溝村下塗溝","塗溝村頂塗溝"],"ㄋ":["內溪村內溪洲","內溪村溪仔底","南和村","南和村南靖","南和村後寮","南鄉村","南鄉村牛稠埔","南鄉村鹿寮"],"ㄌ":["六合街","立業街","良都街","柳林村柳子林","柳鄉村柳子林","柳新村柳子林","凌雲二村","龍德村","龍德村十一指厝","龍德街"],"ㄍ":["國姓村三界埔"],"ㄎ":["寬士村","寬士村崎子頭"],"ㄏ":["回歸村北回","和平街","華林街"],"ㄐ":["九如街","建國四村","進學街","靖和村南靖農場","靖和村南靖糖廠","嘉朴路"],"ㄑ":["七賢街","溪洲村外溪洲"],"ㄒ":["下寮村","下寮村下寮","下寮村鴿溪寮","信義街","新進街","溪洲村外溪洲"],"ㄓ":["中山路二段","中山路三段","中正路","中庄村中庄","中和路","中華路","中義路","中興路","正義路","忠孝街","忠和村中庄","忠和村石仔缸","忠和村紅毛寮","忠和村檳榔樹角","莊敬街"],"ㄔ":["成功街"],"ㄕ":["十全街","水上村水上","水上村外林","水上村店仔後","水德路","水頭村","水頭村水上","水頭村吳竹仔腳","市政街","信義街","順興街"],"ㄖ":["仁愛街","榮典路"],"ㄗ":["自強街"],"ㄘ":["粗溪村","粗溪村巷口","粗溪村粗溪","慈雲十村"],"ㄙ":["三多街","三和村頂寮","三和村新和庄","三和村新厝仔","三界村三界埔","三界村下庄尾","三鎮村","三鎮村南靖車站","三鎮路","四維街"],"ㄚ":[],"ㄛ":[],"ㄜ":[],"ㄝ":[],"ㄞ":[],"ㄟ":[],"ㄠ":[],"ㄡ":[],"ㄢ":[],"ㄣ":[],"ㄤ":[],"ㄥ":[],"ㄦ":["二聖街"],"ㄧ":["一心街","義德街","義興村下菜園","義興村紅毛寮","義興村埤寮","義興村番子寮","義興村溪洲仔"],"ㄨ":["五福街","外林街","吳竹街","萬能路"],"ㄩ":[]},
        "鹿草鄉":{"ㄅ":["碧潭村頂潭"],"ㄆ":[],"ㄇ":["馬稠後園區一路","馬稠後園區二路","馬稠後園區三路"],"ㄈ":["豐稠村信義新村","豐稠村海豐","豐稠村馬稠後","豐稠村維新新村"],"ㄉ":[],"ㄊ":[],"ㄋ":[],"ㄌ":["鹿東村鹿草","鹿草村鹿草","鹿草路","鹿環北路","鹿環西路","鹿環東路","鹿環南路","豊稠村馬稠後農場"],"ㄍ":["光潭村下潭"],"ㄎ":[],"ㄏ":["後堀村山子脚","後堀村後堀","後寮村後寮"],"ㄐ":[],"ㄑ":[],"ㄒ":["下麻村下半天","下麻村下麻","下麻村頂半天","下麻村麻豆店","下麻村過溝子","下潭村下潭","西井村鹿草","西井村鹿草農場","西井村鎮平"],"ㄓ":["竹山村竹子脚","竹山村亀佛山","長壽路","重寮村中寮"],"ㄔ":["長壽路","重寮村中寮"],"ㄕ":["施家村施厝寮"],"ㄖ":[],"ㄗ":[],"ㄘ":[],"ㄙ":["三角村三角子","三角村毛蟹行","松竹村竹子脚"],"ㄚ":[],"ㄛ":[],"ㄜ":[],"ㄝ":[],"ㄞ":[],"ㄟ":[],"ㄠ":[],"ㄡ":[],"ㄢ":["安和街"],"ㄣ":[],"ㄤ":[],"ㄥ":[],"ㄦ":[],"ㄧ":[],"ㄨ":["文康街"],"ㄩ":["圓山路"]},
        "太保市":{"ㄅ":["八德街","北港路二段","北新里新廍","北新里溪底寮","北興路","保鐵一路","保鐵一路三段","保鐵七路","保鐵九路","保鐵二路","保鐵八路","保鐵三路","保鐵五路","保鐵六路","埤鄉里","埤鄉里中島農場","埤鄉里埤麻脚","埤鄉里埤麻腳農場","博愛路","博學路","棒球一街","棒球二街","棒球三街"],"ㄆ":["埤鄉里","埤鄉里中島農場","埤鄉里埤麻脚","埤鄉里埤麻腳農場"],"ㄇ":["民生路","梅埔里埔心","梅埔里梅子厝","麻太路"],"ㄈ":[],"ㄉ":["東勢里東勢寮","鼎新街"],"ㄊ":["太子大道","太保一路","太保二路","太保三路","太保五路","太保里太保","田尾里田尾","田尾里溪南"],"ㄋ":["南埤路"],"ㄌ":["六合街","崙頂里崙子頂","崙頂里橋子頭"],"ㄍ":["公園北街","公園南街","故宮大道","高鐵大道","高鐵西路","港尾里","港尾里白鴿厝農場","港尾里魚寮","港尾里港尾","港尾里管事厝","過溝里瓦厝","過溝里過溝"],"ㄎ":[],"ㄏ":["合德新村","和平路","後庄里太保農場","後庄里後庄","後潭里後潭"],"ㄐ":["健康路","嘉太工業區中興路","嘉太工業區光復路","嘉太工業區和順路","嘉太工業區建工路","嘉太工業區嘉太路","嘉太工業區興業路","嘉朴東路一段","舊埤里新埤","舊埤里龍昇新村"],"ㄑ":["前潭里後潭","前潭里銘泰新村"],"ㄒ":["信義二路","祥和一路東段","祥和二路東段","祥和三路東段","新平路","新合街","新安一街","新安七街","新安二街","新安八街","新安三街","新安五街","新安六街","新安四街","新埤里新埤","學府路一段","縣府一街","縣府二街","縣府三街","縣府五街","縣府六街"],"ㄓ":["中山新城","中山路一段","中山路二段","中正路","中興路一段","中興路二段","致善一街","致善二街"],"ㄔ":["春珠里春珠","春珠里茄苳脚","崇善路","誠信街"],"ㄕ":["信義二路","雙合街"],"ㄖ":["仁愛路"],"ㄗ":[],"ㄘ":[],"ㄙ":["三合路"],"ㄚ":[],"ㄛ":[],"ㄜ":[],"ㄝ":[],"ㄞ":[],"ㄟ":[],"ㄠ":[],"ㄡ":[],"ㄢ":["安仁里三塊厝","安仁里頂港子墘"],"ㄣ":[],"ㄤ":[],"ㄥ":[],"ㄦ":[],"ㄧ":[],"ㄨ":["文化北街","文化南街","文昌街"],"ㄩ":[]},
        "朴子市":{"ㄅ":["八德路","北通路","博文街","博愛街"],"ㄆ":["平安路","平和路","朴子一路","朴子七路","朴子二路","朴子三路","朴子工業區一街","朴子工業區二街","朴子工業區三街","朴子工業區五街","朴子工業區六街","朴子工業區四街","朴子工業區橫一街","朴子工業區橫二街","朴子五路","朴子六路","朴東一街","朴東二街","朴東三街"],"ㄇ":["明智路","梅華里牛挑灣"],"ㄈ":["府西七街","府西二街","府西三街","府西六街"],"ㄉ":["大同東路","大同路","大鄉里大康榔","大葛里大康榔","第一市場","第一市場中央","第二市場","德家里吳竹子腳","德興里新吉庄"],"ㄊ":["天星新村"],"ㄋ":["內厝里內厝","南竹里南勢竹","南通路三段"],"ㄌ":["黎明路"],"ㄍ":["公園一街","公園二街","光明街","光復新路","光復路","果菜市場","故宮大道"],"ㄎ":["崁前里崁前","崁後里崁後","開元路"],"ㄏ":["海通路"],"ㄐ":["介壽路","吉祥一街","吉祥七街","吉祥二街","吉祥三街","吉祥五街西段","吉祥五街東段","吉祥六街","佳禾里大館","佳禾里東安寮","佳禾里苦瓜寮","嘉朴路西段"],"ㄑ":["溪口里雙溪口"],"ㄒ":["小槺榔一路","小槺榔二路","小槺榔五路","向榮路","祥和一路","祥和一路西段","祥和二路","祥和二路西段","祥和三路西段","新民街","新生街","新庄里新庄","新進路","新榮路","新寮里新寮","新興路","溪口里雙溪口","學府路一段","學府路二段"],"ㄓ":["中正路","中興路","竹村里鴨母寮","竹圍里下竹圍","長庚一路","長庚二路"],"ㄔ":["長庚一路","長庚二路"],"ㄕ":["山通路","市西路","市東路","順安里龜子港","雙溪里雙溪口"],"ㄖ":["仁和一路","仁和二路","仁和里小康榔"],"ㄗ":["自立路"],"ㄘ":[],"ㄙ":["三安路","四維新路","四維路一段","四維路二段","四維路三段","四維路四段","松華里牛挑灣"],"ㄚ":[],"ㄛ":[],"ㄜ":[],"ㄝ":[],"ㄞ":[],"ㄟ":[],"ㄠ":[],"ㄡ":[],"ㄢ":[],"ㄣ":[],"ㄤ":[],"ㄥ":[],"ㄦ":[],"ㄧ":["友愛街"],"ㄨ":["文化北路","文化南路","文明南路","文明路","維新街"],"ㄩ":["永和里105-17巷","永和里應菜埔"]},
        "東石鄉":{"ㄅ":[],"ㄆ":[],"ㄇ":[],"ㄈ":["副瀨村副瀨","副瀨村新結庄"],"ㄉ":["東石村東石","東石村黎明","東石村黎明","東崙村中洲","東崙村栗子崙","頂揖村頂揖子寮","頂揖村灣子埔"],"ㄊ":[],"ㄋ":["蔦松村下蔦松","蔦松村船子頭","蔦松村湖底"],"ㄌ":["黎明一路","黎明七路","黎明二路","黎明八路","黎明三路","黎明五路","黎明六路","龍港村頂厝子","龍港村港墘厝"],"ㄍ":["港口村蚶子寮","港林街","港墘村港墘","觀海一路","觀海二路","觀海三路"],"ㄎ":[],"ㄏ":["海埔村海埔"],"ㄐ":[],"ㄑ":["溪下村下舊子埔","溪下村溪子下","溪下村舊子埔"],"ㄒ":["下揖村下揖子寮","西崙村栗子崙","型厝村山寮","型厝村型厝寮","新生一街","新生二街","新生三街","溪下村下舊子埔","溪下村溪子下","溪下村舊子埔"],"ㄓ":["長樂街","洲仔村洲子","掌潭村白水湖","掌潭村掌潭"],"ㄔ":["長樂街"],"ㄕ":[],"ㄖ":[],"ㄗ":[],"ㄘ":["彩霞大道"],"ㄙ":["三家村三塊厝"],"ㄚ":[],"ㄛ":[],"ㄜ":[],"ㄝ":[],"ㄞ":[],"ㄟ":[],"ㄠ":["鰲鼓村四股","鰲鼓村鰲鼓"],"ㄡ":[],"ㄢ":[],"ㄣ":[],"ㄤ":[],"ㄥ":[],"ㄦ":[],"ㄧ":[],"ㄨ":["圍潭村双連潭","圍潭村圍子內","塭仔村後埔","塭仔村塭子","塭港村塭港","網寮村網寮","網寮村鹽田"],"ㄩ":["永屯村屯子頭","猿樹村東石","猿樹村頂寮"]},
        "六腳鄉":{"ㄅ":["崩山村前崩山","崩山村後崩山"],"ㄆ":[],"ㄇ":[],"ㄈ":["豐美村港尾寮"],"ㄉ":[],"ㄊ":["塗師村塗師","潭墘村潭子墘"],"ㄋ":[],"ㄌ":["六斗村六斗尾","六斗村新厝","六斗段地號","六南村六腳","六腳村六腳","崙陽村","崙陽段地號"],"ㄍ":["工廠村蒜頭糖廠","古林村林內","更寮村更寮","港美村港尾寮"],"ㄎ":[],"ㄏ":[],"ㄐ":["更寮村更寮"],"ㄑ":["溪厝村溪墘厝"],"ㄒ":["溪厝村溪墘厝"],"ㄓ":["正義村下雙溪","正義村大橋頭","正義村中溝","正義村占富厝","竹本村竹子腳"],"ㄔ":[],"ㄕ":["樹仁路","雙涵村雙涵"],"ㄖ":[],"ㄗ":[],"ㄘ":[],"ㄙ":["三義村三姓寮","蒜東村蒜頭","蒜南村蒜頭","蒜頭市場","蒜頭村蒜頭","蒜頭糖廠單身宿舍","蘇厝村蘇厝寮","蘇厝段地號"],"ㄚ":[],"ㄛ":[],"ㄜ":[],"ㄝ":[],"ㄞ":[],"ㄟ":[],"ㄠ":[],"ㄡ":[],"ㄢ":[],"ㄣ":[],"ㄤ":[],"ㄥ":[],"ㄦ":[],"ㄧ":[],"ㄨ":["灣北村灣內","灣南村灣內"],"ㄩ":["永賢村竹子腳","魚寮村魚寮"]},
        "新港鄉":{"ㄅ":["北崙村崙子","板頭村板頭厝","板頭村灣子內","板頭段地號","埤子村埤子頭","埤頭段地號"],"ㄆ":["埤子村埤子頭","埤頭段地號"],"ㄇ":[],"ㄈ":["奉天路","福德路"],"ㄉ":["大安街","大崙段地號","大潭村大潭","大潭村後底湖","大興路","登雲路"],"ㄊ":["潭大村","潭大村大竹圍","潭大村大客","潭大村六斗子","潭大村潭子墘","潭大村藍子厝"],"ㄋ":["南崙村崙子","南崙村溪底寮","南港村大崙","南港村竹圍子","南港村南港","南港村菜園","南港村農場","南港村農場","南港村舊南港","南港段地號"],"ㄌ":[],"ㄍ":["公園路","古民村古民","古民街","共和村","共和村後庄","共和村洪厝","共和村頂菜園","共和村黃厝","共和村董厝","共和村藍子厝","共和段地號","宮後街"],"ㄎ":[],"ㄏ":["海瀛村海豐子","海瀛村潭底子"],"ㄐ":["嘉北路","嘉民北路","嘉民路","舊南港段地號"],"ㄑ":["溪北村溪北"],"ㄒ":["西庄村西庄","新中路","新民路","新東街","新港市場","溪北村溪北"],"ㄓ":["中山路","中山路奉天大廈","中正路","中庄村中庄","中洋村中洋子","中洋村中洋工業區","中洋村後厝子"],"ㄔ":[],"ㄕ":[],"ㄖ":[],"ㄗ":[],"ㄘ":["菜公村","菜公村咬仔竹","菜公村菜公厝","菜園段地號"],"ㄙ":["三間村三間厝","三間村港尾","三間村鑽石新城"],"ㄚ":[],"ㄛ":[],"ㄜ":[],"ㄝ":[],"ㄞ":[],"ㄟ":[],"ㄠ":[],"ㄡ":[],"ㄢ":["安和村","安和村番婆","安和村新部落"],"ㄣ":[],"ㄤ":[],"ㄥ":[],"ㄦ":[],"ㄧ":["藝高路"],"ㄨ":["文昌街","灣仔內段地號"],"ㄩ":["月眉村月眉潭","月潭村月眉潭"]},
        "民雄鄉":{"ㄅ":["北斗村北勢子","北斗村新庄子","北斗村覆鼎金","保生街","保安街"],"ㄆ":["平和村柴頭仔","平和村頂店仔","平和村番仔溝","平和村雙援"],"ㄇ":["民生路","民族路","民祥新村","民新東路","民新路","民新路","民溪南路","民溪路","民農一街","民農二街","民農路","民樂街","民權路"],"ㄈ":["富義新村","富農一街","富農二街","富農路","復興路","福樂村埤角","福興村牛稠溪","福興村新興","福權村下寮","福權村福權","豐收村","豐收村山子腳","豐收村好收","豐收村竹圍後"],"ㄉ":["大崎村十四甲","大崎村大丘園","大崎村大崎腳","大崎村內埔仔","大崎村頂埤仔","大學路一段","大學路二段","大學路三段","東湖村","東湖村東勢湖","東榮村下土庫仔","東榮村中庄","東榮路","東興村田寮","東興村葉子寮","頂崙村崙子頂"],"ㄊ":[],"ㄋ":["南華路二段"],"ㄌ":["立全新村","立德街","寮頂村","寮頂村下寮","寮頂村頂寮"],"ㄍ":["工業一路","工業二路","工業三路","工業五路","公園一街","公園二街","公園路","光明一街","光明二街","光明三街","光明五街","光明六街","光明四街","光明街"],"ㄎ":[],"ㄏ":["和平路","惠安街"],"ㄐ":["金興村頭橋","建國路一段","建國路二段","建國路三段","菁埔村內菁埔","菁埔村菁埔","進興街","集福街"],"ㄑ":[],"ㄒ":["西安村菜園","西安路","西昌村竹子腳","秀林村火炭埔","秀林村東義","秀林村林子尾","秀林村溪仔尾","秀林村溪底寮","協同新村","新正一街","新正二街","新正八街","新正三街","新正五街","新正六街","新生一街","新生街","新忠路","興中村江厝仔","興中村江厝店","興中村坔墘","興中村義橋","興中村劉竹仔腳","興南村下洋仔","興南村頭橋","興農一街","興農二街","興農三街","興農路"],"ㄓ":["中山路","中央村","中央村田中央","中央村新庄","中正路","中和村社溝","中和村原吉仔","中和村魚寮仔","中華路","中樂村下土庫仔","中樂路","中樂路市場","中興一街","中興街","正大路","正大路一段","正大路二段","正大路三段","正義一街","正義二街","正義三街","正義路","忠義街","長安街","長榮街","鎮北村土庫子","鎮北村圳溝墘","鎮北村虎尾寮"],"ㄔ":["成功一街","成功二街","成功三街","成功五街","成功四街","成功街","長安街","長榮街"],"ㄕ":["山中村牛斗山","升學一街","升學二街","升學路","昇平路","神農一街","神農二街","神農三街","神農五街","神農路","雙福村雙福"],"ㄖ":["仁德街","瑞豐路"],"ㄗ":["自強一街","自強二街"],"ㄘ":[],"ㄙ":["三興一街","三興二街","三興村竹圍後","三興村陳厝寮","三興村溪底廍","三興路","三豐路","松山村坑底","松山村東湖仔","松山村松子腳","松山村後山仔"],"ㄚ":[],"ㄛ":[],"ㄜ":[],"ㄝ":[],"ㄞ":[],"ㄟ":[],"ㄠ":[],"ㄡ":[],"ㄢ":["安和路"],"ㄣ":[],"ㄤ":[],"ㄥ":[],"ㄦ":[],"ㄧ":[],"ㄨ":["文化路","文隆村山腳","文隆村鴨母坔","文學路","武昌街"],"ㄩ":["裕農一街","裕農路"]},
        "大林鎮":{"ㄅ":["八德街"],"ㄆ":["平和街","平林里下潭底","平林里水源新城","平林里平林國宅","平林里過溝仔","平林里樊厝","平林里潭底零售市場","排路里水汴頭","排路里排子路"],"ㄇ":["民生北路","民生路","民族北路","民族路","民權路","明和里","明和里甘蔗崙","明華里下埤頭","明華里湖底","明華路"],"ㄈ":["福德市場"],"ㄉ":["大民北路","大美里大埔美","大美里互助社區","大美里崎頂","大美里新崎頭","大埔美園區一路","大埔美園區七路","大埔美園區九路","大埔美園區二十路","大埔美園區二路","大埔美園區十二路","大埔美園區十八路","大埔美園區十六路","大埔美園區三路","大埔美園區五路","大埔美園區五路北段","大埔美園區六路","大智一街","大智二街","大智三街","大智五街","大糖里大湖農場","大糖里中學","大糖里糖廠","東榮街","德卿街"],"ㄊ":[],"ㄋ":["內林里內林","南華路一段"],"ㄌ":["蘭洲街"],"ㄍ":["公園路","光明街","光彩街","光華街","共和街","溝背里尾厝","溝背里溝背","過溪里永祿新城","過溪里油車店","過溪里崎頂","過溪里崎頂營區","過溪里崎頭","過溪里新崎頭","過溪里過溪"],"ㄎ":[],"ㄏ":["湖北里大湖","湖北里早知"],"ㄐ":[],"ㄑ":[],"ㄒ":["西林里中興一路","西結里","西結里陳井寮","西結里菜園","西榮路","信義街","祥和路","新興街"],"ㄓ":["中山路","中正新村","中正路","中坑里中坑","中坑里中興","中坑里田寮","中坑里沙崙","中坑里芎蕉山","中坑里埤頭","中坑里崩埤仔","中坑里精北營區","中坑里精南營區","中林里下潭底","中林里下潭底","中林里中林","中興路","中興路二段","正隆新村","忠孝路","莊敬街"],"ㄔ":[],"ㄕ":["上林里頂員林","上林里麻園寮","水源路","信義街"],"ㄖ":["仁愛路","瑞德北路","瑞德路","榮信新村"],"ㄗ":["自強街"],"ㄘ":[],"ㄙ":["三村里湖子","三村里潭墘","三村里橋子頭","三角里三角","三角里下林頭","三角里北勢","三角里林頭","三角里社團新村","三和里水碓","三和里林子前","三和里林子頭","四維街"],"ㄚ":[],"ㄛ":[],"ㄜ":[],"ㄝ":[],"ㄞ":[],"ㄟ":[],"ㄠ":[],"ㄡ":[],"ㄢ":[],"ㄣ":[],"ㄤ":[],"ㄥ":[],"ㄦ":[],"ㄧ":["義和里","義和里三塊厝"],"ㄨ":[],"ㄩ":["育才街","育英街"]},
        "溪口鄉":{"ㄅ":["本厝村本廳","本厝村厝子"],"ㄆ":["坪頂村下坪","坪頂村竹圍仔","坪頂村頂坪","坪頂村菜園"],"ㄇ":["民生街","民族西路","民族東路","民權街","妙崙村上崙","妙崙村下崙","妙崙村新興庄","美北村崙尾","美南村天赦","美南村崙尾"],"ㄈ":[],"ㄉ":["疊溪村三疊溪","疊溪村下員林"],"ㄊ":[],"ㄋ":[],"ㄌ":["林腳村田心仔","林腳村柴林腳","柳溝村阿連庄","柳溝村南靖厝","柳溝村柳子溝"],"ㄍ":[],"ㄎ":[],"ㄏ":["和平街"],"ㄐ":[],"ㄑ":["溪中路","溪北村小柴林腳","溪北村後港","溪北村溝明","溪民路"],"ㄒ":["信義街","新生街","溪中路","溪北村小柴林腳","溪北村後港","溪北村溝明","溪民路"],"ㄓ":["中山路","中正東路","中正路","中興街","忠孝街","忠義街"],"ㄔ":["成功路","柴林村柴林腳"],"ㄕ":["信義街"],"ㄖ":["仁愛街"],"ㄗ":[],"ㄘ":[],"ㄙ":[],"ㄚ":[],"ㄛ":[],"ㄜ":[],"ㄝ":[],"ㄞ":[],"ㄟ":[],"ㄠ":[],"ㄡ":[],"ㄢ":[],"ㄣ":[],"ㄤ":[],"ㄥ":[],"ㄦ":[],"ㄧ":["游西村潭肚寮","游東村牛埔寮","游東村米粉宮","游東村游厝庄","游東村舊庄"],"ㄨ":[],"ㄩ":[]},
        "義竹鄉":{"ㄅ":["北華村北港子","埤前村三脚貓","埤前村埤子頭"],"ㄆ":["平溪村安溪寮","平溪村槺榔港","埤前村三脚貓","埤前村埤子頭"],"ㄇ":[],"ㄈ":[],"ㄉ":["東光村岸內農場","東光村東後寮","東光村新庄","東過村過路子","東榮村西後寮","東榮村東後寮"],"ㄊ":["頭竹村下寮","頭竹村頭竹圍"],"ㄋ":[],"ㄌ":["六桂村義竹","六桂村義竹第一市場","龍蛟村瓦磘","龍蛟村草湖","龍蛟村龍蛟潭"],"ㄍ":["官和村芊子寮","官順村芊子寮"],"ㄎ":[],"ㄏ":["後鎮村後鎮"],"ㄐ":[],"ㄑ":["溪洲村上溪洲","溪洲村下溪洲","溪洲村溪洲農場"],"ㄒ":["西過村過路子","新店村新店","新富村牛稠底","新富村林仔內","溪洲村上溪洲","溪洲村下溪洲","溪洲村溪洲農場"],"ㄓ":["中平村七塊厝","中平村中庄","中平村田尾","傳芳村義竹"],"ㄔ":["傳芳村義竹"],"ㄕ":[],"ㄖ":["仁里村義竹"],"ㄗ":[],"ㄘ":[],"ㄙ":[],"ㄚ":[],"ㄛ":[],"ㄜ":[],"ㄝ":[],"ㄞ":[],"ㄟ":[],"ㄠ":[],"ㄡ":[],"ㄢ":["岸腳村角帶圍","岸腳村岸腳"],"ㄣ":[],"ㄤ":[],"ㄥ":[],"ㄦ":[],"ㄧ":["義工一路","義工二路","義工三路","義竹村義竹"],"ㄨ":["五厝村五間厝"],"ㄩ":[]},
        "布袋鎮":{"ㄅ":["博愛一街","博愛二街","碧沙街"],"ㄆ":[],"ㄇ":[],"ㄈ":["復興里新塭"],"ㄉ":["大智街","東安里過溝東勢頭","東港里東港","東港里埔仔厝"],"ㄊ":["太平東路","太平路"],"ㄋ":[],"ㄌ":["龍江里新厝仔","臨海路"],"ㄍ":["光復里六棟寮","光復里半路店","光復里東安庄","光復路一段","光復路二段","光復路三段","貴舍里半月","貴舍里貴舍"],"ㄎ":["考試里考試潭","考試里鹿寮仔"],"ㄏ":["好美里虎尾寮","後寮南路","後寮路","海平街","海安街","海利街","海順街","海運街","海興街","海豐街","環河街"],"ㄐ":["九龍一街","九龍二街","九龍三街","九龍六街","江山里崩山","見龍里內田"],"ㄑ":["清水街"],"ㄒ":["西安里過溝西勢","西安里過溝厦厝","信義街","新中街","新北一街","新北二街","新北三街","新北五街","新北六街","新北路","新民里新塭","新西一街","新西路","新岑里郭岑寮","新南一街","新南二街","新南三街","新南路","新厝里新厝仔","興中里半路店","興中街"],"ㄓ":["中山路","中正路","中安里金京林","中安里過溝中厝","中安里過溝頂厝","中安里鹽地仔","忠孝街","振寮里後壁寮"],"ㄔ":[],"ㄕ":["上海一街","上海二街","上海東路","上海路","信義街","順安路","樹林里下庄仔","樹林里港後","樹林里樹林頭"],"ㄖ":["入船路","仁愛街"],"ㄗ":["自由路"],"ㄘ":["菜舖里洲仔寮","菜舖里菜舖廍","菜舖里新吉庄"],"ㄙ":[],"ㄚ":[],"ㄛ":[],"ㄜ":[],"ㄝ":[],"ㄞ":[],"ㄟ":[],"ㄠ":[],"ㄡ":[],"ㄢ":[],"ㄣ":[],"ㄤ":[],"ㄥ":[],"ㄦ":[],"ㄧ":[],"ㄨ":["文昌街"],"ㄩ":["永安里大寮","永樂街"]}
    }
}